{
  "id": "0b194f1f-c470-442b-8e96-5eb90c8c7c73",
  "prevId": "8feba020-cd24-4514-8726-9ad36e031abc",
  "version": "7",
  "dialect": "postgresql",
  "tables": {
    "public.email_otp_sessions": {
      "name": "email_otp_sessions",
      "schema": "",
      "columns": {
        "id": {
          "name": "id",
          "type": "uuid",
          "primaryKey": true,
          "notNull": true,
          "default": "gen_random_uuid()"
        },
        "email": {
          "name": "email",
          "type": "varchar(255)",
          "primaryKey": false,
          "notNull": true
        },
        "code_hash": {
          "name": "code_hash",
          "type": "varchar(128)",
          "primaryKey": false,
          "notNull": true
        },
        "status": {
          "name": "status",
          "type": "wa_login_status",
          "typeSchema": "public",
          "primaryKey": false,
          "notNull": true,
          "default": "'pending'"
        },
        "attempts": {
          "name": "attempts",
          "type": "integer",
          "primaryKey": false,
          "notNull": true,
          "default": 0
        },
        "created_at": {
          "name": "created_at",
          "type": "timestamp with time zone",
          "primaryKey": false,
          "notNull": true,
          "default": "now()"
        },
        "expires_at": {
          "name": "expires_at",
          "type": "timestamp with time zone",
          "primaryKey": false,
          "notNull": true
        },
        "verified_at": {
          "name": "verified_at",
          "type": "timestamp with time zone",
          "primaryKey": false,
          "notNull": false
        }
      },
      "indexes": {},
      "foreignKeys": {},
      "compositePrimaryKeys": {},
      "uniqueConstraints": {},
      "policies": {},
      "checkConstraints": {},
      "isRLSEnabled": false
    },
    "public.users": {
      "name": "users",
      "schema": "",
      "columns": {
        "id": {
          "name": "id",
          "type": "uuid",
          "primaryKey": true,
          "notNull": true,
          "default": "gen_random_uuid()"
        },
        "email": {
          "name": "email",
          "type": "varchar(255)",
          "primaryKey": false,
          "notNull": false
        },
        "whatsapp": {
          "name": "whatsapp",
          "type": "varchar(32)",
          "primaryKey": false,
          "notNull": false
        },
        "full_name": {
          "name": "full_name",
          "type": "varchar(255)",
          "primaryKey": false,
          "notNull": false
        },
        "plan_type": {
          "name": "plan_type",
          "type": "plan_type",
          "typeSchema": "public",
          "primaryKey": false,
          "notNull": true,
          "default": "'freemium'"
        },
        "plan_started_at": {
          "name": "plan_started_at",
          "type": "timestamp with time zone",
          "primaryKey": false,
          "notNull": false
        },
        "plan_expired_at": {
          "name": "plan_expired_at",
          "type": "timestamp with time zone",
          "primaryKey": false,
          "notNull": false
        },
        "is_active": {
          "name": "is_active",
          "type": "boolean",
          "primaryKey": false,
          "notNull": true,
          "default": true
        },
        "is_suspended": {
          "name": "is_suspended",
          "type": "boolean",
          "primaryKey": false,
          "notNull": true,
          "default": false
        },
        "created_at": {
          "name": "created_at",
          "type": "timestamp with time zone",
          "primaryKey": false,
          "notNull": true,
          "default": "now()"
        },
        "updated_at": {
          "name": "updated_at",
          "type": "timestamp with time zone",
          "primaryKey": false,
          "notNull": true,
          "default": "now()"
        }
      },
      "indexes": {},
      "foreignKeys": {},
      "compositePrimaryKeys": {},
      "uniqueConstraints": {
        "users_email_unique": {
          "name": "users_email_unique",
          "nullsNotDistinct": false,
          "columns": [
            "email"
          ]
        },
        "users_whatsapp_unique": {
          "name": "users_whatsapp_unique",
          "nullsNotDistinct": false,
          "columns": [
            "whatsapp"
          ]
        }
      },
      "policies": {},
      "checkConstraints": {},
      "isRLSEnabled": false
    },
    "public.wa_login_sessions": {
      "name": "wa_login_sessions",
      "schema": "",
      "columns": {
        "code": {
          "name": "code",
          "type": "varchar(20)",
          "primaryKey": true,
          "notNull": true
        },
        "wa_number": {
          "name": "wa_number",
          "type": "varchar(32)",
          "primaryKey": false,
          "notNull": false
        },
        "status": {
          "name": "status",
          "type": "wa_login_status",
          "typeSchema": "public",
          "primaryKey": false,
          "notNull": true,
          "default": "'pending'"
        },
        "callback_token": {
          "name": "callback_token",
          "type": "varchar(64)",
          "primaryKey": false,
          "notNull": true
        },
        "created_at": {
          "name": "created_at",
          "type": "timestamp with time zone",
          "primaryKey": false,
          "notNull": true,
          "default": "now()"
        },
        "verified_at": {
          "name": "verified_at",
          "type": "timestamp with time zone",
          "primaryKey": false,
          "notNull": false
        }
      },
      "indexes": {},
      "foreignKeys": {},
      "compositePrimaryKeys": {},
      "uniqueConstraints": {
        "wa_login_sessions_callback_token_unique": {
          "name": "wa_login_sessions_callback_token_unique",
          "nullsNotDistinct": false,
          "columns": [
            "callback_token"
          ]
        }
      },
      "policies": {},
      "checkConstraints": {},
      "isRLSEnabled": false
    },
    "public.wallet_transactions": {
      "name": "wallet_transactions",
      "schema": "",
      "columns": {
        "id": {
          "name": "id",
          "type": "uuid",
          "primaryKey": true,
          "notNull": true,
          "default": "gen_random_uuid()"
        },
        "wallet_id": {
          "name": "wallet_id",
          "type": "uuid",
          "primaryKey": false,
          "notNull": true
        },
        "type": {
          "name": "type",
          "type": "wallet_tx_type",
          "typeSchema": "public",
          "primaryKey": false,
          "notNull": true
        },
        "amount": {
          "name": "amount",
          "type": "numeric(15, 2)",
          "primaryKey": false,
          "notNull": true
        },
        "balance_before": {
          "name": "balance_before",
          "type": "numeric(15, 2)",
          "primaryKey": false,
          "notNull": true
        },
        "balance_after": {
          "name": "balance_after",
          "type": "numeric(15, 2)",
          "primaryKey": false,
          "notNull": true
        },
        "reference_id": {
          "name": "reference_id",
          "type": "varchar(255)",
          "primaryKey": false,
          "notNull": false
        },
        "description": {
          "name": "description",
          "type": "varchar(500)",
          "primaryKey": false,
          "notNull": false
        },
        "created_at": {
          "name": "created_at",
          "type": "timestamp with time zone",
          "primaryKey": false,
          "notNull": true,
          "default": "now()"
        }
      },
      "indexes": {},
      "foreignKeys": {
        "wallet_transactions_wallet_id_wallets_id_fk": {
          "name": "wallet_transactions_wallet_id_wallets_id_fk",
          "tableFrom": "wallet_transactions",
          "tableTo": "wallets",
          "columnsFrom": [
            "wallet_id"
          ],
          "columnsTo": [
            "id"
          ],
          "onDelete": "cascade",
          "onUpdate": "no action"
        }
      },
      "compositePrimaryKeys": {},
      "uniqueConstraints": {},
      "policies": {},
      "checkConstraints": {},
      "isRLSEnabled": false
    },
    "public.wallets": {
      "name": "wallets",
      "schema": "",
      "columns": {
        "id": {
          "name": "id",
          "type": "uuid",
          "primaryKey": true,
          "notNull": true,
          "default": "gen_random_uuid()"
        },
        "user_id": {
          "name": "user_id",
          "type": "uuid",
          "primaryKey": false,
          "notNull": true
        },
        "balance": {
          "name": "balance",
          "type": "numeric(15, 2)",
          "primaryKey": false,
          "notNull": true,
          "default": "'0'"
        },
        "currency": {
          "name": "currency",
          "type": "varchar(8)",
          "primaryKey": false,
          "notNull": true,
          "default": "'IDR'"
        },
        "updated_at": {
          "name": "updated_at",
          "type": "timestamp with time zone",
          "primaryKey": false,
          "notNull": true,
          "default": "now()"
        }
      },
      "indexes": {},
      "foreignKeys": {
        "wallets_user_id_users_id_fk": {
          "name": "wallets_user_id_users_id_fk",
          "tableFrom": "wallets",
          "tableTo": "users",
          "columnsFrom": [
            "user_id"
          ],
          "columnsTo": [
            "id"
          ],
          "onDelete": "cascade",
          "onUpdate": "no action"
        }
      },
      "compositePrimaryKeys": {},
      "uniqueConstraints": {
        "wallets_user_id_unique": {
          "name": "wallets_user_id_unique",
          "nullsNotDistinct": false,
          "columns": [
            "user_id"
          ]
        }
      },
      "policies": {},
      "checkConstraints": {},
      "isRLSEnabled": false
    },
    "public.shops": {
      "name": "shops",
      "schema": "",
      "columns": {
        "id": {
          "name": "id",
          "type": "uuid",
          "primaryKey": true,
          "notNull": true,
          "default": "gen_random_uuid()"
        },
        "user_id": {
          "name": "user_id",
          "type": "uuid",
          "primaryKey": false,
          "notNull": true
        },
        "marketplace": {
          "name": "marketplace",
          "type": "marketplace",
          "typeSchema": "public",
          "primaryKey": false,
          "notNull": true
        },
        "shop_id": {
          "name": "shop_id",
          "type": "varchar(128)",
          "primaryKey": false,
          "notNull": true
        },
        "shop_name": {
          "name": "shop_name",
          "type": "varchar(255)",
          "primaryKey": false,
          "notNull": false
        },
        "shop_cipher": {
          "name": "shop_cipher",
          "type": "varchar(255)",
          "primaryKey": false,
          "notNull": false
        },
        "open_id": {
          "name": "open_id",
          "type": "varchar(255)",
          "primaryKey": false,
          "notNull": false
        },
        "merchant_id": {
          "name": "merchant_id",
          "type": "varchar(255)",
          "primaryKey": false,
          "notNull": false
        },
        "seller_region": {
          "name": "seller_region",
          "type": "varchar(8)",
          "primaryKey": false,
          "notNull": false
        },
        "access_token": {
          "name": "access_token",
          "type": "text",
          "primaryKey": false,
          "notNull": false
        },
        "access_token_expire_at": {
          "name": "access_token_expire_at",
          "type": "timestamp with time zone",
          "primaryKey": false,
          "notNull": false
        },
        "refresh_token": {
          "name": "refresh_token",
          "type": "text",
          "primaryKey": false,
          "notNull": false
        },
        "refresh_token_expire_at": {
          "name": "refresh_token_expire_at",
          "type": "timestamp with time zone",
          "primaryKey": false,
          "notNull": false
        },
        "shop_status": {
          "name": "shop_status",
          "type": "shop_status",
          "typeSchema": "public",
          "primaryKey": false,
          "notNull": true,
          "default": "'active'"
        },
        "last_sync_at": {
          "name": "last_sync_at",
          "type": "timestamp with time zone",
          "primaryKey": false,
          "notNull": false
        },
        "connected_at": {
          "name": "connected_at",
          "type": "timestamp with time zone",
          "primaryKey": false,
          "notNull": false
        },
        "created_at": {
          "name": "created_at",
          "type": "timestamp with time zone",
          "primaryKey": false,
          "notNull": true,
          "default": "now()"
        }
      },
      "indexes": {
        "shops_user_idx": {
          "name": "shops_user_idx",
          "columns": [
            {
              "expression": "user_id",
              "isExpression": false,
              "asc": true,
              "nulls": "last"
            }
          ],
          "isUnique": false,
          "concurrently": false,
          "method": "btree",
          "with": {}
        },
        "shops_mp_shop_idx": {
          "name": "shops_mp_shop_idx",
          "columns": [
            {
              "expression": "marketplace",
              "isExpression": false,
              "asc": true,
              "nulls": "last"
            },
            {
              "expression": "shop_id",
              "isExpression": false,
              "asc": true,
              "nulls": "last"
            }
          ],
          "isUnique": false,
          "concurrently": false,
          "method": "btree",
          "with": {}
        }
      },
      "foreignKeys": {
        "shops_user_id_users_id_fk": {
          "name": "shops_user_id_users_id_fk",
          "tableFrom": "shops",
          "tableTo": "users",
          "columnsFrom": [
            "user_id"
          ],
          "columnsTo": [
            "id"
          ],
          "onDelete": "cascade",
          "onUpdate": "no action"
        }
      },
      "compositePrimaryKeys": {},
      "uniqueConstraints": {},
      "policies": {},
      "checkConstraints": {},
      "isRLSEnabled": false
    },
    "public.bom_items": {
      "name": "bom_items",
      "schema": "",
      "columns": {
        "id": {
          "name": "id",
          "type": "uuid",
          "primaryKey": true,
          "notNull": true,
          "default": "gen_random_uuid()"
        },
        "master_product_id": {
          "name": "master_product_id",
          "type": "uuid",
          "primaryKey": false,
          "notNull": true
        },
        "material_name": {
          "name": "material_name",
          "type": "varchar(255)",
          "primaryKey": false,
          "notNull": true
        },
        "quantity": {
          "name": "quantity",
          "type": "numeric(10, 3)",
          "primaryKey": false,
          "notNull": true
        },
        "unit": {
          "name": "unit",
          "type": "varchar(32)",
          "primaryKey": false,
          "notNull": false
        },
        "current_stock": {
          "name": "current_stock",
          "type": "numeric(10, 3)",
          "primaryKey": false,
          "notNull": true,
          "default": "'0'"
        },
        "minimum_threshold": {
          "name": "minimum_threshold",
          "type": "numeric(10, 3)",
          "primaryKey": false,
          "notNull": true,
          "default": "'0'"
        },
        "restock_method": {
          "name": "restock_method",
          "type": "restock_method",
          "typeSchema": "public",
          "primaryKey": false,
          "notNull": true,
          "default": "'wa_owner'"
        },
        "supplier_name": {
          "name": "supplier_name",
          "type": "varchar(255)",
          "primaryKey": false,
          "notNull": false
        },
        "supplier_shopee_url": {
          "name": "supplier_shopee_url",
          "type": "varchar(1000)",
          "primaryKey": false,
          "notNull": false
        },
        "supplier_wa_number": {
          "name": "supplier_wa_number",
          "type": "varchar(32)",
          "primaryKey": false,
          "notNull": false
        },
        "supplier_api_url": {
          "name": "supplier_api_url",
          "type": "varchar(1000)",
          "primaryKey": false,
          "notNull": false
        },
        "supplier_api_key": {
          "name": "supplier_api_key",
          "type": "text",
          "primaryKey": false,
          "notNull": false
        },
        "restock_qty": {
          "name": "restock_qty",
          "type": "numeric(10, 3)",
          "primaryKey": false,
          "notNull": false
        },
        "restock_price": {
          "name": "restock_price",
          "type": "numeric(15, 2)",
          "primaryKey": false,
          "notNull": false
        },
        "payment_method": {
          "name": "payment_method",
          "type": "varchar(32)",
          "primaryKey": false,
          "notNull": false
        },
        "shipping_address": {
          "name": "shipping_address",
          "type": "text",
          "primaryKey": false,
          "notNull": false
        },
        "receiver_name": {
          "name": "receiver_name",
          "type": "varchar(255)",
          "primaryKey": false,
          "notNull": false
        },
        "receiver_phone": {
          "name": "receiver_phone",
          "type": "varchar(32)",
          "primaryKey": false,
          "notNull": false
        },
        "notes_for_supplier": {
          "name": "notes_for_supplier",
          "type": "text",
          "primaryKey": false,
          "notNull": false
        },
        "created_at": {
          "name": "created_at",
          "type": "timestamp with time zone",
          "primaryKey": false,
          "notNull": true,
          "default": "now()"
        }
      },
      "indexes": {},
      "foreignKeys": {
        "bom_items_master_product_id_master_products_id_fk": {
          "name": "bom_items_master_product_id_master_products_id_fk",
          "tableFrom": "bom_items",
          "tableTo": "master_products",
          "columnsFrom": [
            "master_product_id"
          ],
          "columnsTo": [
            "id"
          ],
          "onDelete": "cascade",
          "onUpdate": "no action"
        }
      },
      "compositePrimaryKeys": {},
      "uniqueConstraints": {},
      "policies": {},
      "checkConstraints": {},
      "isRLSEnabled": false
    },
    "public.master_product_variants": {
      "name": "master_product_variants",
      "schema": "",
      "columns": {
        "id": {
          "name": "id",
          "type": "uuid",
          "primaryKey": true,
          "notNull": true,
          "default": "gen_random_uuid()"
        },
        "master_product_id": {
          "name": "master_product_id",
          "type": "uuid",
          "primaryKey": false,
          "notNull": true
        },
        "sku": {
          "name": "sku",
          "type": "varchar(128)",
          "primaryKey": false,
          "notNull": true
        },
        "variant_name": {
          "name": "variant_name",
          "type": "varchar(255)",
          "primaryKey": false,
          "notNull": false
        },
        "price": {
          "name": "price",
          "type": "numeric(15, 2)",
          "primaryKey": false,
          "notNull": false
        },
        "stock": {
          "name": "stock",
          "type": "integer",
          "primaryKey": false,
          "notNull": true,
          "default": 0
        },
        "images": {
          "name": "images",
          "type": "jsonb",
          "primaryKey": false,
          "notNull": false,
          "default": "'[]'::jsonb"
        },
        "created_at": {
          "name": "created_at",
          "type": "timestamp with time zone",
          "primaryKey": false,
          "notNull": true,
          "default": "now()"
        }
      },
      "indexes": {},
      "foreignKeys": {
        "master_product_variants_master_product_id_master_products_id_fk": {
          "name": "master_product_variants_master_product_id_master_products_id_fk",
          "tableFrom": "master_product_variants",
          "tableTo": "master_products",
          "columnsFrom": [
            "master_product_id"
          ],
          "columnsTo": [
            "id"
          ],
          "onDelete": "cascade",
          "onUpdate": "no action"
        }
      },
      "compositePrimaryKeys": {},
      "uniqueConstraints": {},
      "policies": {},
      "checkConstraints": {},
      "isRLSEnabled": false
    },
    "public.master_products": {
      "name": "master_products",
      "schema": "",
      "columns": {
        "id": {
          "name": "id",
          "type": "uuid",
          "primaryKey": true,
          "notNull": true,
          "default": "gen_random_uuid()"
        },
        "user_id": {
          "name": "user_id",
          "type": "uuid",
          "primaryKey": false,
          "notNull": true
        },
        "sku": {
          "name": "sku",
          "type": "varchar(128)",
          "primaryKey": false,
          "notNull": true
        },
        "name": {
          "name": "name",
          "type": "varchar(255)",
          "primaryKey": false,
          "notNull": true
        },
        "description": {
          "name": "description",
          "type": "text",
          "primaryKey": false,
          "notNull": false
        },
        "category_id": {
          "name": "category_id",
          "type": "integer",
          "primaryKey": false,
          "notNull": false
        },
        "base_price": {
          "name": "base_price",
          "type": "numeric(15, 2)",
          "primaryKey": false,
          "notNull": false
        },
        "weight_gram": {
          "name": "weight_gram",
          "type": "integer",
          "primaryKey": false,
          "notNull": false
        },
        "images": {
          "name": "images",
          "type": "jsonb",
          "primaryKey": false,
          "notNull": false,
          "default": "'[]'::jsonb"
        },
        "status": {
          "name": "status",
          "type": "product_status",
          "typeSchema": "public",
          "primaryKey": false,
          "notNull": true,
          "default": "'draft'"
        },
        "health_score": {
          "name": "health_score",
          "type": "health_score",
          "typeSchema": "public",
          "primaryKey": false,
          "notNull": false
        },
        "created_at": {
          "name": "created_at",
          "type": "timestamp with time zone",
          "primaryKey": false,
          "notNull": true,
          "default": "now()"
        },
        "updated_at": {
          "name": "updated_at",
          "type": "timestamp with time zone",
          "primaryKey": false,
          "notNull": true,
          "default": "now()"
        }
      },
      "indexes": {
        "master_products_user_idx": {
          "name": "master_products_user_idx",
          "columns": [
            {
              "expression": "user_id",
              "isExpression": false,
              "asc": true,
              "nulls": "last"
            }
          ],
          "isUnique": false,
          "concurrently": false,
          "method": "btree",
          "with": {}
        }
      },
      "foreignKeys": {
        "master_products_user_id_users_id_fk": {
          "name": "master_products_user_id_users_id_fk",
          "tableFrom": "master_products",
          "tableTo": "users",
          "columnsFrom": [
            "user_id"
          ],
          "columnsTo": [
            "id"
          ],
          "onDelete": "cascade",
          "onUpdate": "no action"
        }
      },
      "compositePrimaryKeys": {},
      "uniqueConstraints": {
        "master_products_user_sku_unique": {
          "name": "master_products_user_sku_unique",
          "nullsNotDistinct": false,
          "columns": [
            "user_id",
            "sku"
          ]
        }
      },
      "policies": {},
      "checkConstraints": {},
      "isRLSEnabled": false
    },
    "public.product_postings": {
      "name": "product_postings",
      "schema": "",
      "columns": {
        "id": {
          "name": "id",
          "type": "uuid",
          "primaryKey": true,
          "notNull": true,
          "default": "gen_random_uuid()"
        },
        "master_product_id": {
          "name": "master_product_id",
          "type": "uuid",
          "primaryKey": false,
          "notNull": true
        },
        "shop_id": {
          "name": "shop_id",
          "type": "uuid",
          "primaryKey": false,
          "notNull": true
        },
        "marketplace_item_id": {
          "name": "marketplace_item_id",
          "type": "varchar(128)",
          "primaryKey": false,
          "notNull": false
        },
        "marketplace_sku": {
          "name": "marketplace_sku",
          "type": "varchar(128)",
          "primaryKey": false,
          "notNull": false
        },
        "title": {
          "name": "title",
          "type": "varchar(500)",
          "primaryKey": false,
          "notNull": false
        },
        "price": {
          "name": "price",
          "type": "numeric(15, 2)",
          "primaryKey": false,
          "notNull": false
        },
        "stock": {
          "name": "stock",
          "type": "integer",
          "primaryKey": false,
          "notNull": false
        },
        "status": {
          "name": "status",
          "type": "posting_status",
          "typeSchema": "public",
          "primaryKey": false,
          "notNull": true,
          "default": "'active'"
        },
        "views_7d": {
          "name": "views_7d",
          "type": "integer",
          "primaryKey": false,
          "notNull": true,
          "default": 0
        },
        "sold_7d": {
          "name": "sold_7d",
          "type": "integer",
          "primaryKey": false,
          "notNull": true,
          "default": 0
        },
        "gmv_7d": {
          "name": "gmv_7d",
          "type": "numeric(15, 2)",
          "primaryKey": false,
          "notNull": true,
          "default": "'0'"
        },
        "review_score": {
          "name": "review_score",
          "type": "numeric(3, 2)",
          "primaryKey": false,
          "notNull": false
        },
        "review_count": {
          "name": "review_count",
          "type": "integer",
          "primaryKey": false,
          "notNull": true,
          "default": 0
        },
        "last_synced_at": {
          "name": "last_synced_at",
          "type": "timestamp with time zone",
          "primaryKey": false,
          "notNull": false
        },
        "created_at": {
          "name": "created_at",
          "type": "timestamp with time zone",
          "primaryKey": false,
          "notNull": true,
          "default": "now()"
        }
      },
      "indexes": {
        "postings_master_idx": {
          "name": "postings_master_idx",
          "columns": [
            {
              "expression": "master_product_id",
              "isExpression": false,
              "asc": true,
              "nulls": "last"
            }
          ],
          "isUnique": false,
          "concurrently": false,
          "method": "btree",
          "with": {}
        },
        "postings_shop_idx": {
          "name": "postings_shop_idx",
          "columns": [
            {
              "expression": "shop_id",
              "isExpression": false,
              "asc": true,
              "nulls": "last"
            }
          ],
          "isUnique": false,
          "concurrently": false,
          "method": "btree",
          "with": {}
        },
        "postings_mp_sku_idx": {
          "name": "postings_mp_sku_idx",
          "columns": [
            {
              "expression": "marketplace_sku",
              "isExpression": false,
              "asc": true,
              "nulls": "last"
            }
          ],
          "isUnique": false,
          "concurrently": false,
          "method": "btree",
          "with": {}
        }
      },
      "foreignKeys": {
        "product_postings_master_product_id_master_products_id_fk": {
          "name": "product_postings_master_product_id_master_products_id_fk",
          "tableFrom": "product_postings",
          "tableTo": "master_products",
          "columnsFrom": [
            "master_product_id"
          ],
          "columnsTo": [
            "id"
          ],
          "onDelete": "cascade",
          "onUpdate": "no action"
        },
        "product_postings_shop_id_shops_id_fk": {
          "name": "product_postings_shop_id_shops_id_fk",
          "tableFrom": "product_postings",
          "tableTo": "shops",
          "columnsFrom": [
            "shop_id"
          ],
          "columnsTo": [
            "id"
          ],
          "onDelete": "cascade",
          "onUpdate": "no action"
        }
      },
      "compositePrimaryKeys": {},
      "uniqueConstraints": {},
      "policies": {},
      "checkConstraints": {},
      "isRLSEnabled": false
    },
    "public.orders": {
      "name": "orders",
      "schema": "",
      "columns": {
        "id": {
          "name": "id",
          "type": "uuid",
          "primaryKey": true,
          "notNull": true,
          "default": "gen_random_uuid()"
        },
        "user_id": {
          "name": "user_id",
          "type": "uuid",
          "primaryKey": false,
          "notNull": true
        },
        "shop_id": {
          "name": "shop_id",
          "type": "uuid",
          "primaryKey": false,
          "notNull": true
        },
        "marketplace_order_id": {
          "name": "marketplace_order_id",
          "type": "varchar(128)",
          "primaryKey": false,
          "notNull": true
        },
        "marketplace": {
          "name": "marketplace",
          "type": "marketplace",
          "typeSchema": "public",
          "primaryKey": false,
          "notNull": true
        },
        "status": {
          "name": "status",
          "type": "varchar(64)",
          "primaryKey": false,
          "notNull": false
        },
        "fulfillment_status": {
          "name": "fulfillment_status",
          "type": "fulfillment_status",
          "typeSchema": "public",
          "primaryKey": false,
          "notNull": true,
          "default": "'masuk'"
        },
        "buyer_name": {
          "name": "buyer_name",
          "type": "varchar(255)",
          "primaryKey": false,
          "notNull": false
        },
        "buyer_phone": {
          "name": "buyer_phone",
          "type": "varchar(32)",
          "primaryKey": false,
          "notNull": false
        },
        "shipping_address": {
          "name": "shipping_address",
          "type": "jsonb",
          "primaryKey": false,
          "notNull": false
        },
        "shipping_courier": {
          "name": "shipping_courier",
          "type": "varchar(128)",
          "primaryKey": false,
          "notNull": false
        },
        "tracking_number": {
          "name": "tracking_number",
          "type": "varchar(128)",
          "primaryKey": false,
          "notNull": false
        },
        "payment_method": {
          "name": "payment_method",
          "type": "varchar(64)",
          "primaryKey": false,
          "notNull": false
        },
        "subtotal": {
          "name": "subtotal",
          "type": "numeric(15, 2)",
          "primaryKey": false,
          "notNull": false
        },
        "shipping_fee": {
          "name": "shipping_fee",
          "type": "numeric(15, 2)",
          "primaryKey": false,
          "notNull": false
        },
        "marketplace_fee": {
          "name": "marketplace_fee",
          "type": "numeric(15, 2)",
          "primaryKey": false,
          "notNull": false
        },
        "total_amount": {
          "name": "total_amount",
          "type": "numeric(15, 2)",
          "primaryKey": false,
          "notNull": false
        },
        "platform_fee": {
          "name": "platform_fee",
          "type": "numeric(15, 2)",
          "primaryKey": false,
          "notNull": false
        },
        "fee_deducted": {
          "name": "fee_deducted",
          "type": "boolean",
          "primaryKey": false,
          "notNull": true,
          "default": false
        },
        "awb_generated": {
          "name": "awb_generated",
          "type": "boolean",
          "primaryKey": false,
          "notNull": true,
          "default": false
        },
        "label_printed": {
          "name": "label_printed",
          "type": "boolean",
          "primaryKey": false,
          "notNull": true,
          "default": false
        },
        "items": {
          "name": "items",
          "type": "jsonb",
          "primaryKey": false,
          "notNull": false
        },
        "created_at_marketplace": {
          "name": "created_at_marketplace",
          "type": "timestamp with time zone",
          "primaryKey": false,
          "notNull": false
        },
        "created_at": {
          "name": "created_at",
          "type": "timestamp with time zone",
          "primaryKey": false,
          "notNull": true,
          "default": "now()"
        },
        "updated_at": {
          "name": "updated_at",
          "type": "timestamp with time zone",
          "primaryKey": false,
          "notNull": true,
          "default": "now()"
        }
      },
      "indexes": {
        "orders_user_idx": {
          "name": "orders_user_idx",
          "columns": [
            {
              "expression": "user_id",
              "isExpression": false,
              "asc": true,
              "nulls": "last"
            }
          ],
          "isUnique": false,
          "concurrently": false,
          "method": "btree",
          "with": {}
        },
        "orders_shop_idx": {
          "name": "orders_shop_idx",
          "columns": [
            {
              "expression": "shop_id",
              "isExpression": false,
              "asc": true,
              "nulls": "last"
            }
          ],
          "isUnique": false,
          "concurrently": false,
          "method": "btree",
          "with": {}
        }
      },
      "foreignKeys": {
        "orders_user_id_users_id_fk": {
          "name": "orders_user_id_users_id_fk",
          "tableFrom": "orders",
          "tableTo": "users",
          "columnsFrom": [
            "user_id"
          ],
          "columnsTo": [
            "id"
          ],
          "onDelete": "cascade",
          "onUpdate": "no action"
        },
        "orders_shop_id_shops_id_fk": {
          "name": "orders_shop_id_shops_id_fk",
          "tableFrom": "orders",
          "tableTo": "shops",
          "columnsFrom": [
            "shop_id"
          ],
          "columnsTo": [
            "id"
          ],
          "onDelete": "cascade",
          "onUpdate": "no action"
        }
      },
      "compositePrimaryKeys": {},
      "uniqueConstraints": {
        "orders_mp_order_unique": {
          "name": "orders_mp_order_unique",
          "nullsNotDistinct": false,
          "columns": [
            "marketplace",
            "marketplace_order_id"
          ]
        }
      },
      "policies": {},
      "checkConstraints": {},
      "isRLSEnabled": false
    },
    "public.webhook_events": {
      "name": "webhook_events",
      "schema": "",
      "columns": {
        "id": {
          "name": "id",
          "type": "uuid",
          "primaryKey": true,
          "notNull": true,
          "default": "gen_random_uuid()"
        },
        "marketplace": {
          "name": "marketplace",
          "type": "marketplace",
          "typeSchema": "public",
          "primaryKey": false,
          "notNull": true
        },
        "event_type": {
          "name": "event_type",
          "type": "varchar(128)",
          "primaryKey": false,
          "notNull": false
        },
        "event_id": {
          "name": "event_id",
          "type": "varchar(255)",
          "primaryKey": false,
          "notNull": true
        },
        "shop_id": {
          "name": "shop_id",
          "type": "uuid",
          "primaryKey": false,
          "notNull": false
        },
        "payload": {
          "name": "payload",
          "type": "jsonb",
          "primaryKey": false,
          "notNull": false
        },
        "processed": {
          "name": "processed",
          "type": "boolean",
          "primaryKey": false,
          "notNull": true,
          "default": false
        },
        "processed_at": {
          "name": "processed_at",
          "type": "timestamp with time zone",
          "primaryKey": false,
          "notNull": false
        },
        "error_message": {
          "name": "error_message",
          "type": "text",
          "primaryKey": false,
          "notNull": false
        },
        "created_at": {
          "name": "created_at",
          "type": "timestamp with time zone",
          "primaryKey": false,
          "notNull": true,
          "default": "now()"
        }
      },
      "indexes": {},
      "foreignKeys": {
        "webhook_events_shop_id_shops_id_fk": {
          "name": "webhook_events_shop_id_shops_id_fk",
          "tableFrom": "webhook_events",
          "tableTo": "shops",
          "columnsFrom": [
            "shop_id"
          ],
          "columnsTo": [
            "id"
          ],
          "onDelete": "set null",
          "onUpdate": "no action"
        }
      },
      "compositePrimaryKeys": {},
      "uniqueConstraints": {
        "webhook_events_mp_event_unique": {
          "name": "webhook_events_mp_event_unique",
          "nullsNotDistinct": false,
          "columns": [
            "marketplace",
            "event_id"
          ]
        }
      },
      "policies": {},
      "checkConstraints": {},
      "isRLSEnabled": false
    },
    "public.platform_invoices": {
      "name": "platform_invoices",
      "schema": "",
      "columns": {
        "id": {
          "name": "id",
          "type": "uuid",
          "primaryKey": true,
          "notNull": true,
          "default": "gen_random_uuid()"
        },
        "user_id": {
          "name": "user_id",
          "type": "uuid",
          "primaryKey": false,
          "notNull": true
        },
        "type": {
          "name": "type",
          "type": "invoice_type",
          "typeSchema": "public",
          "primaryKey": false,
          "notNull": true
        },
        "amount": {
          "name": "amount",
          "type": "numeric(15, 2)",
          "primaryKey": false,
          "notNull": true
        },
        "status": {
          "name": "status",
          "type": "invoice_status",
          "typeSchema": "public",
          "primaryKey": false,
          "notNull": true,
          "default": "'pending'"
        },
        "midtrans_order_id": {
          "name": "midtrans_order_id",
          "type": "varchar(255)",
          "primaryKey": false,
          "notNull": false
        },
        "midtrans_payment_url": {
          "name": "midtrans_payment_url",
          "type": "text",
          "primaryKey": false,
          "notNull": false
        },
        "paid_at": {
          "name": "paid_at",
          "type": "timestamp with time zone",
          "primaryKey": false,
          "notNull": false
        },
        "created_at": {
          "name": "created_at",
          "type": "timestamp with time zone",
          "primaryKey": false,
          "notNull": true,
          "default": "now()"
        }
      },
      "indexes": {
        "invoices_user_idx": {
          "name": "invoices_user_idx",
          "columns": [
            {
              "expression": "user_id",
              "isExpression": false,
              "asc": true,
              "nulls": "last"
            }
          ],
          "isUnique": false,
          "concurrently": false,
          "method": "btree",
          "with": {}
        }
      },
      "foreignKeys": {
        "platform_invoices_user_id_users_id_fk": {
          "name": "platform_invoices_user_id_users_id_fk",
          "tableFrom": "platform_invoices",
          "tableTo": "users",
          "columnsFrom": [
            "user_id"
          ],
          "columnsTo": [
            "id"
          ],
          "onDelete": "cascade",
          "onUpdate": "no action"
        }
      },
      "compositePrimaryKeys": {},
      "uniqueConstraints": {},
      "policies": {},
      "checkConstraints": {},
      "isRLSEnabled": false
    },
    "public.pricing_config": {
      "name": "pricing_config",
      "schema": "",
      "columns": {
        "id": {
          "name": "id",
          "type": "uuid",
          "primaryKey": true,
          "notNull": true,
          "default": "gen_random_uuid()"
        },
        "plan_type": {
          "name": "plan_type",
          "type": "plan_type",
          "typeSchema": "public",
          "primaryKey": false,
          "notNull": true
        },
        "setup_fee": {
          "name": "setup_fee",
          "type": "numeric(15, 2)",
          "primaryKey": false,
          "notNull": true,
          "default": "'0'"
        },
        "monthly_fee": {
          "name": "monthly_fee",
          "type": "numeric(15, 2)",
          "primaryKey": false,
          "notNull": true,
          "default": "'0'"
        },
        "per_transaction_fee": {
          "name": "per_transaction_fee",
          "type": "numeric(15, 2)",
          "primaryKey": false,
          "notNull": true,
          "default": "'0'"
        },
        "max_shops": {
          "name": "max_shops",
          "type": "integer",
          "primaryKey": false,
          "notNull": false
        },
        "max_orders_per_month": {
          "name": "max_orders_per_month",
          "type": "integer",
          "primaryKey": false,
          "notNull": false
        },
        "features": {
          "name": "features",
          "type": "jsonb",
          "primaryKey": false,
          "notNull": false,
          "default": "'{}'::jsonb"
        },
        "is_active": {
          "name": "is_active",
          "type": "boolean",
          "primaryKey": false,
          "notNull": true,
          "default": true
        },
        "updated_at": {
          "name": "updated_at",
          "type": "timestamp with time zone",
          "primaryKey": false,
          "notNull": true,
          "default": "now()"
        }
      },
      "indexes": {},
      "foreignKeys": {},
      "compositePrimaryKeys": {},
      "uniqueConstraints": {},
      "policies": {},
      "checkConstraints": {},
      "isRLSEnabled": false
    },
    "public.affiliates": {
      "name": "affiliates",
      "schema": "",
      "columns": {
        "id": {
          "name": "id",
          "type": "uuid",
          "primaryKey": true,
          "notNull": true,
          "default": "gen_random_uuid()"
        },
        "user_id": {
          "name": "user_id",
          "type": "uuid",
          "primaryKey": false,
          "notNull": true
        },
        "marketplace": {
          "name": "marketplace",
          "type": "marketplace",
          "typeSchema": "public",
          "primaryKey": false,
          "notNull": true
        },
        "creator_id": {
          "name": "creator_id",
          "type": "varchar(128)",
          "primaryKey": false,
          "notNull": false
        },
        "creator_name": {
          "name": "creator_name",
          "type": "varchar(255)",
          "primaryKey": false,
          "notNull": false
        },
        "follower_count": {
          "name": "follower_count",
          "type": "integer",
          "primaryKey": false,
          "notNull": false
        },
        "niche": {
          "name": "niche",
          "type": "varchar(128)",
          "primaryKey": false,
          "notNull": false
        },
        "status": {
          "name": "status",
          "type": "affiliate_status",
          "typeSchema": "public",
          "primaryKey": false,
          "notNull": true,
          "default": "'prospect'"
        },
        "commission_rate": {
          "name": "commission_rate",
          "type": "numeric(5, 2)",
          "primaryKey": false,
          "notNull": false
        },
        "total_gmv": {
          "name": "total_gmv",
          "type": "numeric(15, 2)",
          "primaryKey": false,
          "notNull": true,
          "default": "'0'"
        },
        "notes": {
          "name": "notes",
          "type": "text",
          "primaryKey": false,
          "notNull": false
        },
        "invited_at": {
          "name": "invited_at",
          "type": "timestamp with time zone",
          "primaryKey": false,
          "notNull": false
        },
        "created_at": {
          "name": "created_at",
          "type": "timestamp with time zone",
          "primaryKey": false,
          "notNull": true,
          "default": "now()"
        }
      },
      "indexes": {
        "affiliates_user_idx": {
          "name": "affiliates_user_idx",
          "columns": [
            {
              "expression": "user_id",
              "isExpression": false,
              "asc": true,
              "nulls": "last"
            }
          ],
          "isUnique": false,
          "concurrently": false,
          "method": "btree",
          "with": {}
        }
      },
      "foreignKeys": {
        "affiliates_user_id_users_id_fk": {
          "name": "affiliates_user_id_users_id_fk",
          "tableFrom": "affiliates",
          "tableTo": "users",
          "columnsFrom": [
            "user_id"
          ],
          "columnsTo": [
            "id"
          ],
          "onDelete": "cascade",
          "onUpdate": "no action"
        }
      },
      "compositePrimaryKeys": {},
      "uniqueConstraints": {},
      "policies": {},
      "checkConstraints": {},
      "isRLSEnabled": false
    },
    "public.chat_logs": {
      "name": "chat_logs",
      "schema": "",
      "columns": {
        "id": {
          "name": "id",
          "type": "uuid",
          "primaryKey": true,
          "notNull": true,
          "default": "gen_random_uuid()"
        },
        "shop_id": {
          "name": "shop_id",
          "type": "uuid",
          "primaryKey": false,
          "notNull": true
        },
        "order_id": {
          "name": "order_id",
          "type": "uuid",
          "primaryKey": false,
          "notNull": false
        },
        "chat_type": {
          "name": "chat_type",
          "type": "chat_type",
          "typeSchema": "public",
          "primaryKey": false,
          "notNull": true
        },
        "counterpart_id": {
          "name": "counterpart_id",
          "type": "varchar(128)",
          "primaryKey": false,
          "notNull": false
        },
        "counterpart_name": {
          "name": "counterpart_name",
          "type": "varchar(255)",
          "primaryKey": false,
          "notNull": false
        },
        "message_in": {
          "name": "message_in",
          "type": "text",
          "primaryKey": false,
          "notNull": false
        },
        "message_out": {
          "name": "message_out",
          "type": "text",
          "primaryKey": false,
          "notNull": false
        },
        "ai_model": {
          "name": "ai_model",
          "type": "varchar(128)",
          "primaryKey": false,
          "notNull": false
        },
        "tokens_used": {
          "name": "tokens_used",
          "type": "integer",
          "primaryKey": false,
          "notNull": false
        },
        "marketplace_sent": {
          "name": "marketplace_sent",
          "type": "boolean",
          "primaryKey": false,
          "notNull": true,
          "default": false
        },
        "created_at": {
          "name": "created_at",
          "type": "timestamp with time zone",
          "primaryKey": false,
          "notNull": true,
          "default": "now()"
        }
      },
      "indexes": {},
      "foreignKeys": {
        "chat_logs_shop_id_shops_id_fk": {
          "name": "chat_logs_shop_id_shops_id_fk",
          "tableFrom": "chat_logs",
          "tableTo": "shops",
          "columnsFrom": [
            "shop_id"
          ],
          "columnsTo": [
            "id"
          ],
          "onDelete": "cascade",
          "onUpdate": "no action"
        },
        "chat_logs_order_id_orders_id_fk": {
          "name": "chat_logs_order_id_orders_id_fk",
          "tableFrom": "chat_logs",
          "tableTo": "orders",
          "columnsFrom": [
            "order_id"
          ],
          "columnsTo": [
            "id"
          ],
          "onDelete": "set null",
          "onUpdate": "no action"
        }
      },
      "compositePrimaryKeys": {},
      "uniqueConstraints": {},
      "policies": {},
      "checkConstraints": {},
      "isRLSEnabled": false
    },
    "public.review_logs": {
      "name": "review_logs",
      "schema": "",
      "columns": {
        "id": {
          "name": "id",
          "type": "uuid",
          "primaryKey": true,
          "notNull": true,
          "default": "gen_random_uuid()"
        },
        "shop_id": {
          "name": "shop_id",
          "type": "uuid",
          "primaryKey": false,
          "notNull": true
        },
        "order_id": {
          "name": "order_id",
          "type": "uuid",
          "primaryKey": false,
          "notNull": false
        },
        "marketplace_review_id": {
          "name": "marketplace_review_id",
          "type": "varchar(128)",
          "primaryKey": false,
          "notNull": false
        },
        "rating": {
          "name": "rating",
          "type": "integer",
          "primaryKey": false,
          "notNull": false
        },
        "review_text": {
          "name": "review_text",
          "type": "text",
          "primaryKey": false,
          "notNull": false
        },
        "reply_text": {
          "name": "reply_text",
          "type": "text",
          "primaryKey": false,
          "notNull": false
        },
        "ai_generated": {
          "name": "ai_generated",
          "type": "boolean",
          "primaryKey": false,
          "notNull": true,
          "default": true
        },
        "replied_at": {
          "name": "replied_at",
          "type": "timestamp with time zone",
          "primaryKey": false,
          "notNull": false
        },
        "created_at": {
          "name": "created_at",
          "type": "timestamp with time zone",
          "primaryKey": false,
          "notNull": true,
          "default": "now()"
        }
      },
      "indexes": {},
      "foreignKeys": {
        "review_logs_shop_id_shops_id_fk": {
          "name": "review_logs_shop_id_shops_id_fk",
          "tableFrom": "review_logs",
          "tableTo": "shops",
          "columnsFrom": [
            "shop_id"
          ],
          "columnsTo": [
            "id"
          ],
          "onDelete": "cascade",
          "onUpdate": "no action"
        },
        "review_logs_order_id_orders_id_fk": {
          "name": "review_logs_order_id_orders_id_fk",
          "tableFrom": "review_logs",
          "tableTo": "orders",
          "columnsFrom": [
            "order_id"
          ],
          "columnsTo": [
            "id"
          ],
          "onDelete": "set null",
          "onUpdate": "no action"
        }
      },
      "compositePrimaryKeys": {},
      "uniqueConstraints": {},
      "policies": {},
      "checkConstraints": {},
      "isRLSEnabled": false
    },
    "public.admin_settings": {
      "name": "admin_settings",
      "schema": "",
      "columns": {
        "id": {
          "name": "id",
          "type": "uuid",
          "primaryKey": true,
          "notNull": true,
          "default": "gen_random_uuid()"
        },
        "key": {
          "name": "key",
          "type": "varchar(128)",
          "primaryKey": false,
          "notNull": true
        },
        "value": {
          "name": "value",
          "type": "text",
          "primaryKey": false,
          "notNull": false
        },
        "description": {
          "name": "description",
          "type": "varchar(500)",
          "primaryKey": false,
          "notNull": false
        },
        "updated_by": {
          "name": "updated_by",
          "type": "varchar(128)",
          "primaryKey": false,
          "notNull": false
        },
        "updated_at": {
          "name": "updated_at",
          "type": "timestamp with time zone",
          "primaryKey": false,
          "notNull": true,
          "default": "now()"
        }
      },
      "indexes": {},
      "foreignKeys": {},
      "compositePrimaryKeys": {},
      "uniqueConstraints": {
        "admin_settings_key_unique": {
          "name": "admin_settings_key_unique",
          "nullsNotDistinct": false,
          "columns": [
            "key"
          ]
        }
      },
      "policies": {},
      "checkConstraints": {},
      "isRLSEnabled": false
    },
    "public.notifications": {
      "name": "notifications",
      "schema": "",
      "columns": {
        "id": {
          "name": "id",
          "type": "uuid",
          "primaryKey": true,
          "notNull": true,
          "default": "gen_random_uuid()"
        },
        "user_id": {
          "name": "user_id",
          "type": "uuid",
          "primaryKey": false,
          "notNull": true
        },
        "type": {
          "name": "type",
          "type": "varchar(128)",
          "primaryKey": false,
          "notNull": false
        },
        "title": {
          "name": "title",
          "type": "varchar(255)",
          "primaryKey": false,
          "notNull": false
        },
        "message": {
          "name": "message",
          "type": "text",
          "primaryKey": false,
          "notNull": false
        },
        "channel": {
          "name": "channel",
          "type": "notif_channel",
          "typeSchema": "public",
          "primaryKey": false,
          "notNull": true,
          "default": "'email'"
        },
        "sent": {
          "name": "sent",
          "type": "boolean",
          "primaryKey": false,
          "notNull": true,
          "default": false
        },
        "sent_at": {
          "name": "sent_at",
          "type": "timestamp with time zone",
          "primaryKey": false,
          "notNull": false
        },
        "created_at": {
          "name": "created_at",
          "type": "timestamp with time zone",
          "primaryKey": false,
          "notNull": true,
          "default": "now()"
        }
      },
      "indexes": {},
      "foreignKeys": {
        "notifications_user_id_users_id_fk": {
          "name": "notifications_user_id_users_id_fk",
          "tableFrom": "notifications",
          "tableTo": "users",
          "columnsFrom": [
            "user_id"
          ],
          "columnsTo": [
            "id"
          ],
          "onDelete": "cascade",
          "onUpdate": "no action"
        }
      },
      "compositePrimaryKeys": {},
      "uniqueConstraints": {},
      "policies": {},
      "checkConstraints": {},
      "isRLSEnabled": false
    }
  },
  "enums": {
    "public.affiliate_status": {
      "name": "affiliate_status",
      "schema": "public",
      "values": [
        "prospect",
        "invited",
        "active",
        "rejected",
        "blacklist"
      ]
    },
    "public.chat_type": {
      "name": "chat_type",
      "schema": "public",
      "values": [
        "buyer",
        "affiliate"
      ]
    },
    "public.fulfillment_status": {
      "name": "fulfillment_status",
      "schema": "public",
      "values": [
        "masuk",
        "approved",
        "produksi",
        "packing",
        "siap_kirim",
        "dikirim",
        "selesai",
        "retur",
        "dibatalkan"
      ]
    },
    "public.health_score": {
      "name": "health_score",
      "schema": "public",
      "values": [
        "A",
        "B",
        "C",
        "D"
      ]
    },
    "public.invoice_status": {
      "name": "invoice_status",
      "schema": "public",
      "values": [
        "pending",
        "paid",
        "failed",
        "cancelled"
      ]
    },
    "public.invoice_type": {
      "name": "invoice_type",
      "schema": "public",
      "values": [
        "setup_fee",
        "subscription",
        "topup"
      ]
    },
    "public.marketplace": {
      "name": "marketplace",
      "schema": "public",
      "values": [
        "tiktok",
        "shopee",
        "tokopedia",
        "lazada"
      ]
    },
    "public.notif_channel": {
      "name": "notif_channel",
      "schema": "public",
      "values": [
        "wa",
        "email",
        "in_app"
      ]
    },
    "public.plan_type": {
      "name": "plan_type",
      "schema": "public",
      "values": [
        "freemium",
        "starter",
        "pro"
      ]
    },
    "public.posting_status": {
      "name": "posting_status",
      "schema": "public",
      "values": [
        "active",
        "inactive",
        "deleted",
        "under_review",
        "banned"
      ]
    },
    "public.product_status": {
      "name": "product_status",
      "schema": "public",
      "values": [
        "active",
        "inactive",
        "draft"
      ]
    },
    "public.restock_method": {
      "name": "restock_method",
      "schema": "public",
      "values": [
        "wa_owner",
        "wa_supplier",
        "supplier_api"
      ]
    },
    "public.shop_status": {
      "name": "shop_status",
      "schema": "public",
      "values": [
        "active",
        "deactivated",
        "suspended",
        "disconnected"
      ]
    },
    "public.wa_login_status": {
      "name": "wa_login_status",
      "schema": "public",
      "values": [
        "pending",
        "verified",
        "expired"
      ]
    },
    "public.wallet_tx_type": {
      "name": "wallet_tx_type",
      "schema": "public",
      "values": [
        "topup",
        "deduct_subscription",
        "deduct_transaction",
        "deduct_setup",
        "refund"
      ]
    }
  },
  "schemas": {},
  "sequences": {},
  "roles": {},
  "policies": {},
  "views": {},
  "_meta": {
    "columns": {},
    "schemas": {},
    "tables": {}
  }
}